{
	"name": "",
	"cells": [
		{
			"x": 0,
			"y": 0,
			"w": 140,
			"h": 140,
			"name": "brush_navy"
		},
		{
			"x": 145,
			"y": 0,
			"w": 140,
			"h": 140,
			"name": "brush_white"
		},
		{
			"x": 290,
			"y": 0,
			"w": 140,
			"h": 140,
			"name": "brush_yellow"
		},
		{
			"x": 435,
			"y": 0,
			"w": 140,
			"h": 140,
			"name": "brush_purple"
		},
		{
			"x": 580,
			"y": 0,
			"w": 140,
			"h": 140,
			"name": "brush_red"
		},
		{
			"x": 725,
			"y": 0,
			"w": 140,
			"h": 140,
			"name": "brush_pink"
		},
		{
			"x": 870,
			"y": 0,
			"w": 140,
			"h": 140,
			"name": "brush_green"
		},
		{
			"x": 1015,
			"y": 0,
			"w": 140,
			"h": 140,
			"name": "brush_orange"
		},
		{
			"x": 1160,
			"y": 0,
			"w": 140,
			"h": 140,
			"name": "brush_black"
		},
		{
			"x": 0,
			"y": 145,
			"w": 140,
			"h": 140,
			"name": "brush_cyan"
		},
		{
			"x": 145,
			"y": 145,
			"w": 140,
			"h": 140,
			"name": "brush_blue"
		},
		{
			"x": 290,
			"y": 145,
			"w": 140,
			"h": 140,
			"name": "brush_brown"
		},
		{
			"x": 435,
			"y": 145,
			"w": 210,
			"h": 210,
			"name": "settings_down_3"
		},
		{
			"x": 650,
			"y": 145,
			"w": 210,
			"h": 210,
			"name": "settings_down_5"
		},
		{
			"x": 865,
			"y": 145,
			"w": 210,
			"h": 210,
			"name": "settings_down_4"
		},
		{
			"x": 1080,
			"y": 145,
			"w": 210,
			"h": 210,
			"name": "settings_down_2"
		},
		{
			"x": 0,
			"y": 360,
			"w": 210,
			"h": 210,
			"name": "settings_down_1"
		},
		{
			"x": 215,
			"y": 360,
			"w": 210,
			"h": 210,
			"name": "back"
		},
		{
			"x": 430,
			"y": 360,
			"w": 210,
			"h": 210,
			"name": "back_down"
		},
		{
			"x": 645,
			"y": 360,
			"w": 210,
			"h": 210,
			"name": "settings"
		},
		{
			"x": 1065,
			"y": 1425,
			"w": 350,
			"h": 350,
			"name": "tile_animals"
		},
		{
			"x": 355,
			"y": 1425,
			"w": 350,
			"h": 350,
			"name": "tile_animals_down"
		},
		{
			"x": 710,
			"y": 1425,
			"w": 350,
			"h": 350,
			"name": "tile_colouring"
		},
		{
			"x": 355,
			"y": 1070,
			"w": 350,
			"h": 350,
			"name": "tile_colouring_down"
		},
		{
			"x": 710,
			"y": 715,
			"w": 350,
			"h": 350,
			"name": "tile_match"
		},
		{
			"x": 0,
			"y": 715,
			"w": 350,
			"h": 350,
			"name": "tile_match_down"
		},
		{
			"x": 860,
			"y": 360,
			"w": 350,
			"h": 350,
			"name": "tile_numbers"
		},
		{
			"x": 0,
			"y": 1070,
			"w": 350,
			"h": 350,
			"name": "tile_numbers_down"
		},
		{
			"x": 355,
			"y": 715,
			"w": 350,
			"h": 350,
			"name": "tile_shapes"
		},
		{
			"x": 1065,
			"y": 715,
			"w": 350,
			"h": 350,
			"name": "tile_shapes_down"
		},
		{
			"x": 710,
			"y": 1070,
			"w": 350,
			"h": 350,
			"name": "one"
		},
		{
			"x": 1065,
			"y": 1070,
			"w": 350,
			"h": 350,
			"name": "two"
		},
		{
			"x": 0,
			"y": 1425,
			"w": 350,
			"h": 350,
			"name": "three"
		}
	]
}